ECMPY/AutoPACMEN_function.py
ECMPY/ECMpy_function.py
ECMPY/__init__.py
ECMPY/get_ecGEM_onestop.py
ECMPY/model.py
ECMPY/prediction_for_input.py
BIOecmpy-2.0.dist-info/METADATA
BIOecmpy-2.0.dist-info/WHEEL
BIOecmpy-2.0.dist-info/top_level.txt
BIOecmpy-2.0.dist-info/RECORD
