Metadata-Version: 2.1
Name: BIOecmpy
Version: 2.0
Summary: Automated construction of enzyme constraint models using ECMpy workflow
Home-page: https://github.com/A-runaaaa/ecmpy
Author: TIB BioDesign Center
License: MIT
Requires-Dist: requests
Requires-Dist: pebble
Requires-Dist: xlsxwriter
Requires-Dist: Bio
Requires-Dist: Require
Requires-Dist: quest
Requires-Dist: scikit-learn
Requires-Dist: RDKit
Requires-Dist: seaborn
Requires-Dist: pubchempy
Requires-Dist: torch
Requires-Dist: ipykernel
Requires-Dist: bioservices (==1.10.4)
Requires-Dist: pyprobar
Requires-Dist: xmltodict
